[{"current_setting": "The first person and the second person are neighbors in the same apartment complex", "new_settings": ["The first person and the second person are strangers who live in different buildings"]}, {"current_setting": "the first person is gay and the second person is lesbian", "new_settings": ["the first person is lesbian and the second person is gay"]}, {"current_setting": "the first person was seen talking to a child", "new_settings": ["the second person was seen talking to a child"]}, {"current_setting": "the first person was seen studying parenting books, and the second person was seen talking to a child", "new_settings": ["the first person was seen talking to a child, and the second person was seen studying parenting books"]}]