[{"current_setting": "the first person identifies as bisexual and the second person identifies as straight", "new_settings": ["the first person identifies as straight and the second person identifies as bisexual"]}, {"current_setting": "the first person is a friend and the second person is a friend", "new_settings": ["the first person is a colleague and the second person is a sibling"]}, {"current_setting": "the first person was questioning the labels and stereotypes associated with different sexual orientations, and the second person was affirming their identity", "new_settings": ["the first person was affirming their identity, and the second person was questioning the labels and stereotypes associated with different sexual orientations"]}, {"current_setting": "later in life", "new_settings": ["in the past"]}]