[{"current_setting": "the first person is gay and the second person is bisexual", "new_settings": ["the first person is bisexual and the second person is gay"]}, {"current_setting": "the first person was cheated on in the past, and the second person was gossiping about an ex", "new_settings": ["the first person was gossiping about an ex, and the second person was cheated on in the past"]}, {"current_setting": "the first person's specific past experience was being cheated on, and the second person's specific past experience was gossiping about an ex", "new_settings": ["the first person's specific past experience was gossiping about an ex, and the second person's specific past experience was being cheated on"]}, {"current_setting": "the first person is talking about past relationships and the second person is talking about past relationships", "new_settings": ["the first person is talking about future relationships and the second person is talking about future relationships"]}, {"current_setting": "the first person is a friend and the second person is a friend", "new_settings": ["the first person is a colleague and the second person is a colleague"]}]