{
  "intervention_str": "00001",
  "old_values": [
    "no checking account",
    6,
    "all credits at this bank paid back duly",
    "others",
    7352.0
  ],
  "new_values": [
    "no checking account",
    6,
    "all credits at this bank paid back duly",
    "others",
    6248.0
  ],
  "parsed_counterfactual": {
    "edited_question": {
      "status": "no checking account",
      "duration": 6,
      "credit_history": "all credits at this bank paid back duly",
      "purpose": "others",
      "amount": 6248.0
    }
  }
}