[{"concept": "status", "current_setting": "balance less than 0 Euro", "new_settings": ["balance at least 200 Euro or salary for at least 1 year"]}, {"concept": "duration", "current_setting": 18, "new_settings": [27]}, {"concept": "credit_history", "current_setting": "all credits at this bank paid back duly", "new_settings": ["existing credits paid back duly till now"]}, {"concept": "purpose", "current_setting": "car (used)", "new_settings": ["furniture/equipment"]}, {"concept": "amount", "current_setting": 12722.0, "new_settings": [9052.0]}]